{
  "categories" : [ {
    "id" : "accompaniments",
    "name" : "Apke Sath Mey (Accompaniments)",
    "dishes" : [ {
      "id" : "papad",
      "name" : "Papad",
      "price" : 16,
      "image" : "static/images/dishes/papad.jpg",
      "description" : "",
      "available" : false,
      "tags" : [ ],
      "alt_text" : "Papad",
      "category_id" : "accompaniments",
      "is_vegetarian" : true,
      "is_vegan" : false,
      "is_spicy" : false
    }, {
      "id" : "papad-fry",
      "name" : "Papad Fry",
      "price" : 25,
      "image" : "static/images/dishes/papad-fry.jpg",
      "description" : "",
      "available" : true,
      "tags" : [ ],
      "alt_text" : "Papad Fry",
      "category_id" : "accompaniments",
      "is_vegetarian" : true,
      "is_vegan" : false,
      "is_spicy" : false
    }, {
      "id" : "papad-masala",
      "name" : "Papad Masala",
      "price" : 60,
      "image" : "static/images/dishes/papad-masala.jpg",
      "description" : "",
      "available" : true,
      "tags" : [ ],
      "alt_text" : "Papad Masala",
      "category_id" : "accompaniments",
      "is_vegetarian" : true,
      "is_vegan" : false,
      "is_spicy" : false
    }, {
      "id" : "plain-curd",
      "name" : "Plain Curd",
      "price" : 70,
      "image" : "static/images/dishes/plain-curd.jpg",
      "description" : "",
      "available" : true,
      "tags" : [ ],
      "alt_text" : "Plain Curd",
      "category_id" : "accompaniments",
      "is_vegetarian" : true,
      "is_vegan" : false,
      "is_spicy" : false
    }, {
      "id" : "veg-raita",
      "name" : "Veg Raita",
      "price" : 89,
      "image" : "static/images/dishes/veg-raita.jpg",
      "description" : "",
      "available" : true,
      "tags" : [ ],
      "alt_text" : "Veg Raita",
      "category_id" : "accompaniments",
      "is_vegetarian" : true,
      "is_vegan" : false,
      "is_spicy" : false
    }, {
      "id" : "boondi-raita",
      "name" : "Boondi Raita",
      "price" : 89,
      "image" : "static/images/dishes/boondi-raita.jpg",
      "description" : "",
      "available" : true,
      "tags" : [ ],
      "alt_text" : "Boondi Raita",
      "category_id" : "accompaniments",
      "is_vegetarian" : true,
      "is_vegan" : false,
      "is_spicy" : false
    }, {
      "id" : "tadka-raita",
      "name" : "Tadka Raita",
      "price" : 89,
      "image" : "static/images/dishes/tadka-raita.jpg",
      "description" : "",
      "available" : true,
      "tags" : [ ],
      "alt_text" : "Tadka Raita",
      "category_id" : "accompaniments",
      "is_vegetarian" : true,
      "is_vegan" : false,
      "is_spicy" : false
    }, {
      "id" : "fruit-raita",
      "name" : "Fruit Raita",
      "price" : 129,
      "image" : "static/images/dishes/fruit-raita.jpg",
      "description" : "",
      "available" : true,
      "tags" : [ ],
      "alt_text" : "Fruit Raita",
      "category_id" : "accompaniments",
      "is_vegetarian" : true,
      "is_vegan" : false,
      "is_spicy" : false
    }, {
      "id" : "pineapple-raita",
      "name" : "Pineapple Raita",
      "price" : 129,
      "image" : "static/images/dishes/pineapple-raita.jpg",
      "description" : "",
      "available" : true,
      "tags" : [ ],
      "alt_text" : "Pineapple Raita",
      "category_id" : "accompaniments",
      "is_vegetarian" : true,
      "is_vegan" : false,
      "is_spicy" : false
    }, {
      "id" : "green-salad",
      "name" : "Green Salad",
      "price" : 72,
      "image" : "static/images/dishes/green-salad.jpg",
      "description" : "",
      "available" : true,
      "tags" : [ ],
      "alt_text" : "Green Salad",
      "category_id" : "accompaniments",
      "is_vegetarian" : true,
      "is_vegan" : false,
      "is_spicy" : false
    }, {
      "id" : "kachumbar-salad",
      "name" : "Kachumbar Salad",
      "price" : 119,
      "image" : "static/images/dishes/kachumbar-salad.jpg",
      "description" : "",
      "available" : true,
      "tags" : [ ],
      "alt_text" : "Kachumbar Salad",
      "category_id" : "accompaniments",
      "is_vegetarian" : true,
      "is_vegan" : false,
      "is_spicy" : false
    }, {
      "id" : "peanut-masala-salad",
      "name" : "Peanut Masala Salad",
      "price" : 129,
      "image" : "static/images/dishes/peanut-masala-salad.jpg",
      "description" : "",
      "available" : true,
      "tags" : [ ],
      "alt_text" : "Peanut Masala Salad",
      "category_id" : "accompaniments",
      "is_vegetarian" : true,
      "is_vegan" : false,
      "is_spicy" : false
    } ],
    "display_order" : 1
  }, {
    "id" : "starters",
    "name" : "Shuruaat (Starters)",
    "dishes" : [ {
      "id" : "french-fries",
      "name" : "French Fries",
      "price" : 149,
      "image" : "static/images/dishes/french-fries.jpg",
      "description" : "",
      "available" : true,
      "tags" : [ ],
      "alt_text" : "French Fries",
      "category_id" : "starters",
      "is_vegetarian" : true,
      "is_vegan" : false,
      "is_spicy" : false
    }, {
      "id" : "pakoda-assorted",
      "name" : "Pakoda Assorted",
      "price" : 169,
      "image" : "static/images/dishes/pakoda-assorted.jpg",
      "description" : "",
      "available" : true,
      "tags" : [ ],
      "alt_text" : "Pakoda Assorted",
      "category_id" : "starters",
      "is_vegetarian" : true,
      "is_vegan" : false,
      "is_spicy" : false
    }, {
      "id" : "chana-chilli",
      "name" : "Chana Chilli",
      "price" : 169,
      "image" : "static/images/dishes/chana-chilli.jpg",
      "description" : "",
      "available" : true,
      "tags" : [ ],
      "alt_text" : "Chana Chilli",
      "category_id" : "starters",
      "is_vegetarian" : true,
      "is_vegan" : false,
      "is_spicy" : false
    }, {
      "id" : "roasted-chana",
      "name" : "Roasted Chana",
      "price" : 209,
      "image" : "static/images/dishes/roasted-chana.jpg",
      "description" : "",
      "available" : true,
      "tags" : [ ],
      "alt_text" : "Roasted Chana",
      "category_id" : "starters",
      "is_vegetarian" : true,
      "is_vegan" : false,
      "is_spicy" : false
    }, {
      "id" : "harabhara-kabab",
      "name" : "Harabhara Kabab",
      "price" : 259,
      "image" : "static/images/dishes/harabhara-kabab.jpg",
      "description" : "",
      "available" : true,
      "tags" : [ ],
      "alt_text" : "Harabhara Kabab",
      "category_id" : "starters",
      "is_vegetarian" : true,
      "is_vegan" : false,
      "is_spicy" : false
    }, {
      "id" : "crispy-corn",
      "name" : "Crispy Corn",
      "price" : 259,
      "image" : "static/images/dishes/crispy-corn.jpg",
      "description" : "",
      "available" : true,
      "tags" : [ ],
      "alt_text" : "Crispy Corn",
      "category_id" : "starters",
      "is_vegetarian" : true,
      "is_vegan" : false,
      "is_spicy" : false
    }, {
      "id" : "crispy-veg",
      "name" : "Crispy Veg",
      "price" : 259,
      "image" : "static/images/dishes/crispy-veg.jpg",
      "description" : "",
      "available" : true,
      "tags" : [ ],
      "alt_text" : "Crispy Veg",
      "category_id" : "starters",
      "is_vegetarian" : true,
      "is_vegan" : false,
      "is_spicy" : false
    }, {
      "id" : "paneer-65",
      "name" : "Paneer 65",
      "price" : 269,
      "image" : "static/images/dishes/paneer-65.jpg",
      "description" : "",
      "available" : true,
      "tags" : [ ],
      "alt_text" : "Paneer 65",
      "category_id" : "starters",
      "is_vegetarian" : true,
      "is_vegan" : false,
      "is_spicy" : false
    }, {
      "id" : "chilli-paneer",
      "name" : "Chilli Paneer",
      "price" : 289,
      "image" : "static/images/dishes/chilli-paneer.jpg",
      "description" : "",
      "available" : true,
      "tags" : [ ],
      "alt_text" : "Chilli Paneer",
      "category_id" : "starters",
      "is_vegetarian" : true,
      "is_vegan" : false,
      "is_spicy" : false
    }, {
      "id" : "paneer-tikka-dry",
      "name" : "Paneer Tikka Dry",
      "price" : 269,
      "image" : "static/images/dishes/paneer-tikka-dry.jpg",
      "description" : "",
      "available" : true,
      "tags" : [ ],
      "alt_text" : "Paneer Tikka Dry",
      "category_id" : "starters",
      "is_vegetarian" : true,
      "is_vegan" : false,
      "is_spicy" : false
    }, {
      "id" : "afghani-chaap",
      "name" : "Afghani Chaap",
      "price" : 269,
      "image" : "static/images/dishes/afghani-chaap.jpg",
      "description" : "",
      "available" : true,
      "tags" : [ ],
      "alt_text" : "Afghani Chaap",
      "category_id" : "starters",
      "is_vegetarian" : true,
      "is_vegan" : false,
      "is_spicy" : false
    } ],
    "display_order" : 2
  }, {
    "id" : "continental",
    "name" : "Dwipiya Bhojan (Continental)",
    "dishes" : [ {
      "id" : "veg-sandwich",
      "name" : "Veg Sandwich",
      "price" : 129,
      "image" : "static/images/dishes/veg-sandwich.jpg",
      "description" : "",
      "available" : true,
      "tags" : [ ],
      "alt_text" : "Veg Sandwich",
      "category_id" : "continental",
      "is_vegetarian" : true,
      "is_vegan" : false,
      "is_spicy" : false
    }, {
      "id" : "grilled-sandwich",
      "name" : "Grilled Sandwich",
      "price" : 149,
      "image" : "static/images/dishes/grilled-sandwich.jpg",
      "description" : "",
      "available" : true,
      "tags" : [ ],
      "alt_text" : "Grilled Sandwich",
      "category_id" : "continental",
      "is_vegetarian" : true,
      "is_vegan" : false,
      "is_spicy" : false
    }, {
      "id" : "veg-cheese-burger",
      "name" : "Veg Cheese Burger",
      "price" : 149,
      "image" : "static/images/dishes/veg-cheese-burger.jpg",
      "description" : "",
      "available" : true,
      "tags" : [ ],
      "alt_text" : "Veg Cheese Burger",
      "category_id" : "continental",
      "is_vegetarian" : true,
      "is_vegan" : false,
      "is_spicy" : false
    }, {
      "id" : "pasta-in-red-sauce",
      "name" : "Pasta In Red Sauce",
      "price" : 189,
      "image" : "static/images/dishes/pasta-red-sauce.jpg",
      "description" : "",
      "available" : true,
      "tags" : [ ],
      "alt_text" : "Pasta In Red Sauce",
      "category_id" : "continental",
      "is_vegetarian" : true,
      "is_vegan" : false,
      "is_spicy" : false
    }, {
      "id" : "pasta-in-white-sauce",
      "name" : "Pasta In White Sauce",
      "price" : 189,
      "image" : "static/images/dishes/pasta-white-sauce.jpg",
      "description" : "",
      "available" : true,
      "tags" : [ ],
      "alt_text" : "Pasta In White Sauce",
      "category_id" : "continental",
      "is_vegetarian" : true,
      "is_vegan" : false,
      "is_spicy" : false
    }, {
      "id" : "pizza-veg",
      "name" : "Pizza Veg",
      "price" : 189,
      "image" : "static/images/dishes/pizza-veg.jpg",
      "description" : "",
      "available" : true,
      "tags" : [ ],
      "alt_text" : "Pizza Veg",
      "category_id" : "continental",
      "is_vegetarian" : true,
      "is_vegan" : false,
      "is_spicy" : false
    }, {
      "id" : "momos-veg-steam/fry",
      "name" : "Momos Veg (Steam/Fry)",
      "price" : 169,
      "image" : "static/images/dishes/momos-veg.jpg",
      "description" : "",
      "available" : true,
      "tags" : [ ],
      "alt_text" : "Momos Veg",
      "category_id" : "continental",
      "is_vegetarian" : true,
      "is_vegan" : false,
      "is_spicy" : false
    }, {
      "id" : "veg-sizzler",
      "name" : "Veg Sizzler",
      "price" : 409,
      "image" : "static/images/dishes/veg-sizzler.jpg",
      "description" : "",
      "available" : true,
      "tags" : [ ],
      "alt_text" : "Veg Sizzler",
      "category_id" : "continental",
      "is_vegetarian" : true,
      "is_vegan" : false,
      "is_spicy" : false
    }, {
      "id" : "chinese-sizzler",
      "name" : "Chinese Sizzler",
      "price" : 409,
      "image" : "static/images/dishes/chinese-sizzler.jpg",
      "description" : "",
      "available" : true,
      "tags" : [ ],
      "alt_text" : "Chinese Sizzler",
      "category_id" : "continental",
      "is_vegetarian" : true,
      "is_vegan" : false,
      "is_spicy" : false
    } ],
    "display_order" : 3
  }, {
    "id" : "chinese",
    "name" : "Chatpati Chinese",
    "dishes" : [ {
      "id" : "veg-kothe",
      "name" : "Veg Kothe",
      "price" : 189,
      "image" : "static/images/dishes/veg-kothe.jpg",
      "description" : "",
      "available" : true,
      "tags" : [ ],
      "alt_text" : "Veg Kothe",
      "category_id" : "chinese",
      "is_vegetarian" : true,
      "is_vegan" : false,
      "is_spicy" : false
    }, {
      "id" : "chowmein-noodles",
      "name" : "Chowmein Noodles",
      "price" : 189,
      "image" : "static/images/dishes/chowmein-noodles.jpg",
      "description" : "",
      "available" : true,
      "tags" : [ ],
      "alt_text" : "Chowmein Noodles",
      "category_id" : "chinese",
      "is_vegetarian" : true,
      "is_vegan" : false,
      "is_spicy" : false
    }, {
      "id" : "hakka-noodles",
      "name" : "Hakka Noodles",
      "price" : 189,
      "image" : "static/images/dishes/hakka-noodles.jpg",
      "description" : "",
      "available" : true,
      "tags" : [ ],
      "alt_text" : "Hakka Noodles",
      "category_id" : "chinese",
      "is_vegetarian" : true,
      "is_vegan" : false,
      "is_spicy" : false
    }, {
      "id" : "schezwan-noodles",
      "name" : "Schezwan Noodles",
      "price" : 189,
      "image" : "static/images/dishes/schezwan-noodles.jpg",
      "description" : "",
      "available" : true,
      "tags" : [ ],
      "alt_text" : "Schezwan Noodles",
      "category_id" : "chinese",
      "is_vegetarian" : true,
      "is_vegan" : false,
      "is_spicy" : false
    }, {
      "id" : "veg-manchurian-gravy/dry",
      "name" : "Veg Manchurian (Gravy/Dry)",
      "price" : 209,
      "image" : "static/images/dishes/veg-manchurian.jpg",
      "description" : "",
      "available" : true,
      "tags" : [ ],
      "alt_text" : "Veg Manchurian",
      "category_id" : "chinese",
      "is_vegetarian" : true,
      "is_vegan" : false,
      "is_spicy" : false
    }, {
      "id" : "honey-chilli-potato",
      "name" : "Honey Chilli Potato",
      "price" : 209,
      "image" : "static/images/dishes/honey-chilli-potato.jpg",
      "description" : "",
      "available" : true,
      "tags" : [ ],
      "alt_text" : "Honey Chilli Potato",
      "category_id" : "chinese",
      "is_vegetarian" : true,
      "is_vegan" : false,
      "is_spicy" : false
    }, {
      "id" : "chilli-paneer-gravy/dry",
      "name" : "Chilli Paneer (Gravy/Dry)",
      "price" : 299,
      "image" : "static/images/dishes/chilli-paneer-chinese.jpg",
      "description" : "",
      "available" : true,
      "tags" : [ ],
      "alt_text" : "Chilli Paneer",
      "category_id" : "chinese",
      "is_vegetarian" : true,
      "is_vegan" : false,
      "is_spicy" : false
    } ],
    "display_order" : 4
  }, {
    "id" : "south-indian",
    "name" : "Dakshini Vyanjan (South Indian)",
    "dishes" : [ {
      "id" : "idli-sambhar",
      "name" : "Idli Sambhar",
      "price" : 89,
      "image" : "static/images/dishes/idli-sambhar.jpg",
      "description" : "",
      "available" : true,
      "tags" : [ ],
      "alt_text" : "Idli Sambhar",
      "category_id" : "south-indian",
      "is_vegetarian" : true,
      "is_vegan" : false,
      "is_spicy" : false
    }, {
      "id" : "uttapam-masala-mix",
      "name" : "Uttapam Masala (Mix)",
      "price" : 109,
      "image" : "static/images/dishes/uttapam-masala.jpg",
      "description" : "",
      "available" : true,
      "tags" : [ ],
      "alt_text" : "Uttapam Masala",
      "category_id" : "south-indian",
      "is_vegetarian" : true,
      "is_vegan" : false,
      "is_spicy" : false
    }, {
      "id" : "masala-dosa",
      "name" : "Masala Dosa",
      "price" : 139,
      "image" : "static/images/dishes/masala-dosa.jpg",
      "description" : "",
      "available" : true,
      "tags" : [ ],
      "alt_text" : "Masala Dosa",
      "category_id" : "south-indian",
      "is_vegetarian" : true,
      "is_vegan" : false,
      "is_spicy" : false
    }, {
      "id" : "mysore-masala-dosa",
      "name" : "Mysore Masala Dosa",
      "price" : 159,
      "image" : "static/images/dishes/mysore-masala-dosa.jpg",
      "description" : "",
      "available" : true,
      "tags" : [ ],
      "alt_text" : "Mysore Masala Dosa",
      "category_id" : "south-indian",
      "is_vegetarian" : true,
      "is_vegan" : false,
      "is_spicy" : false
    }, {
      "id" : "curd-rice",
      "name" : "Curd Rice",
      "price" : 159,
      "image" : "static/images/dishes/curd-rice.jpg",
      "description" : "",
      "available" : true,
      "tags" : [ ],
      "alt_text" : "Curd Rice",
      "category_id" : "south-indian",
      "is_vegetarian" : true,
      "is_vegan" : false,
      "is_spicy" : false
    } ],
    "display_order" : 5
  }, {
    "id" : "vegetables",
    "name" : "Sabjio Ki Jugalbandi (Vegetable Curries)",
    "dishes" : [ {
      "id" : "gobhi-mutter-adrak",
      "name" : "Gobhi Mutter Adrak",
      "price" : 189,
      "image" : "static/images/dishes/gobhi-mutter-adrak.jpg",
      "description" : "",
      "available" : true,
      "tags" : [ ],
      "alt_text" : "Gobhi Mutter Adrak",
      "category_id" : "vegetables",
      "is_vegetarian" : true,
      "is_vegan" : false,
      "is_spicy" : false
    }, {
      "id" : "sev-tomato",
      "name" : "Sev Tomato",
      "price" : 189,
      "image" : "static/images/dishes/sev-tomato.jpg",
      "description" : "",
      "available" : true,
      "tags" : [ ],
      "alt_text" : "Sev Tomato",
      "category_id" : "vegetables",
      "is_vegetarian" : true,
      "is_vegan" : false,
      "is_spicy" : false
    }, {
      "id" : "mix-veg",
      "name" : "Mix Veg",
      "price" : 189,
      "image" : "static/images/dishes/mix-veg.jpg",
      "description" : "",
      "available" : true,
      "tags" : [ ],
      "alt_text" : "Mix Veg",
      "category_id" : "vegetables",
      "is_vegetarian" : true,
      "is_vegan" : false,
      "is_spicy" : false
    }, {
      "id" : "bhindi-masala",
      "name" : "Bhindi Masala",
      "price" : 189,
      "image" : "static/images/dishes/bhindi-masala.jpg",
      "description" : "",
      "available" : true,
      "tags" : [ ],
      "alt_text" : "Bhindi Masala",
      "category_id" : "vegetables",
      "is_vegetarian" : true,
      "is_vegan" : false,
      "is_spicy" : false
    }, {
      "id" : "tomato-masala",
      "name" : "Tomato Masala",
      "price" : 189,
      "image" : "static/images/dishes/tomato-masala.jpg",
      "description" : "",
      "available" : true,
      "tags" : [ ],
      "alt_text" : "Tomato Masala",
      "category_id" : "vegetables",
      "is_vegetarian" : true,
      "is_vegan" : false,
      "is_spicy" : false
    }, {
      "id" : "jeera-aloo",
      "name" : "Jeera Aloo",
      "price" : 189,
      "image" : "static/images/dishes/jeera-aloo.jpg",
      "description" : "",
      "available" : true,
      "tags" : [ ],
      "alt_text" : "Jeera Aloo",
      "category_id" : "vegetables",
      "is_vegetarian" : true,
      "is_vegan" : false,
      "is_spicy" : false
    }, {
      "id" : "chana-masala",
      "name" : "Chana Masala",
      "price" : 169,
      "image" : "static/images/dishes/chana-masala.jpg",
      "description" : "",
      "available" : true,
      "tags" : [ ],
      "alt_text" : "Chana Masala",
      "category_id" : "vegetables",
      "is_vegetarian" : true,
      "is_vegan" : false,
      "is_spicy" : false
    } ],
    "display_order" : 6
  }, {
    "id" : "breads",
    "name" : "Roti (Indian Breads)",
    "dishes" : [ {
      "id" : "tawa-roti",
      "name" : "Tawa Roti",
      "price" : 16,
      "image" : "static/images/dishes/tawa-roti.jpg",
      "description" : "",
      "available" : true,
      "tags" : [ ],
      "alt_text" : "Tawa Roti",
      "category_id" : "breads",
      "is_vegetarian" : true,
      "is_vegan" : false,
      "is_spicy" : false
    }, {
      "id" : "tandoori-roti-plain",
      "name" : "Tandoori Roti Plain",
      "price" : 16,
      "image" : "static/images/dishes/tandoori-roti-plain.jpg",
      "description" : "",
      "available" : true,
      "tags" : [ ],
      "alt_text" : "Tandoori Roti Plain",
      "category_id" : "breads",
      "is_vegetarian" : true,
      "is_vegan" : false,
      "is_spicy" : false
    }, {
      "id" : "tawa-roti-butter",
      "name" : "Tawa Roti Butter",
      "price" : 20,
      "image" : "static/images/dishes/tawa-roti-butter.jpg",
      "description" : "",
      "available" : true,
      "tags" : [ ],
      "alt_text" : "Tawa Roti Butter",
      "category_id" : "breads",
      "is_vegetarian" : true,
      "is_vegan" : false,
      "is_spicy" : false
    }, {
      "id" : "tandoori-roti-butter",
      "name" : "Tandoori Roti Butter",
      "price" : 20,
      "image" : "static/images/dishes/tandoori-roti-butter.jpg",
      "description" : "",
      "available" : true,
      "tags" : [ ],
      "alt_text" : "Tandoori Roti Butter",
      "category_id" : "breads",
      "is_vegetarian" : true,
      "is_vegan" : false,
      "is_spicy" : false
    }, {
      "id" : "butter-naan",
      "name" : "Butter Naan",
      "price" : 50,
      "image" : "static/images/dishes/butter-naan.jpg",
      "description" : "",
      "available" : true,
      "tags" : [ ],
      "alt_text" : "Butter Naan",
      "category_id" : "breads",
      "is_vegetarian" : true,
      "is_vegan" : false,
      "is_spicy" : false
    }, {
      "id" : "missi-roti",
      "name" : "Missi Roti",
      "price" : 45,
      "image" : "static/images/dishes/missi-roti.jpg",
      "description" : "",
      "available" : true,
      "tags" : [ ],
      "alt_text" : "Missi Roti",
      "category_id" : "breads",
      "is_vegetarian" : true,
      "is_vegan" : false,
      "is_spicy" : false
    }, {
      "id" : "laccha-parantha",
      "name" : "Laccha Parantha",
      "price" : 50,
      "image" : "static/images/dishes/laccha-parantha.jpg",
      "description" : "",
      "available" : true,
      "tags" : [ ],
      "alt_text" : "Laccha Parantha",
      "category_id" : "breads",
      "is_vegetarian" : true,
      "is_vegan" : false,
      "is_spicy" : false
    }, {
      "id" : "stuffed-aloo-parantha",
      "name" : "Stuffed Aloo Parantha",
      "price" : 60,
      "image" : "static/images/dishes/stuffed-aloo-parantha.jpg",
      "description" : "",
      "available" : true,
      "tags" : [ ],
      "alt_text" : "Stuffed Aloo Parantha",
      "category_id" : "breads",
      "is_vegetarian" : true,
      "is_vegan" : false,
      "is_spicy" : false
    }, {
      "id" : "aloo-parantha",
      "name" : "Aloo Parantha",
      "price" : 60,
      "image" : "static/images/dishes/aloo-parantha.jpg",
      "description" : "",
      "available" : true,
      "tags" : [ ],
      "alt_text" : "Aloo Parantha",
      "category_id" : "breads",
      "is_vegetarian" : true,
      "is_vegan" : false,
      "is_spicy" : false
    }, {
      "id" : "garlic-cheese-naan",
      "name" : "Garlic Cheese Naan",
      "price" : 70,
      "image" : "static/images/dishes/garlic-cheese-naan.jpg",
      "description" : "",
      "available" : true,
      "tags" : [ ],
      "alt_text" : "Garlic Cheese Naan",
      "category_id" : "breads",
      "is_vegetarian" : true,
      "is_vegan" : false,
      "is_spicy" : false
    } ],
    "display_order" : 7
  }, {
    "id" : "main-course",
    "name" : "Sadabahar (Main Course)",
    "dishes" : [ {
      "id" : "corn-palak",
      "name" : "Corn Palak",
      "price" : 209,
      "image" : "static/images/dishes/corn-palak.jpg",
      "description" : "",
      "available" : true,
      "tags" : [ ],
      "alt_text" : "Corn Palak",
      "category_id" : "main-course",
      "is_vegetarian" : true,
      "is_vegan" : false,
      "is_spicy" : false
    }, {
      "id" : "veg-kolhapuri",
      "name" : "Veg Kolhapuri",
      "price" : 209,
      "image" : "static/images/dishes/veg-kolhapuri.jpg",
      "description" : "",
      "available" : true,
      "tags" : [ ],
      "alt_text" : "Veg Kolhapuri",
      "category_id" : "main-course",
      "is_vegetarian" : true,
      "is_vegan" : false,
      "is_spicy" : false
    }, {
      "id" : "veg-jalfrezi",
      "name" : "Veg Jalfrezi",
      "price" : 209,
      "image" : "static/images/dishes/veg-jalfrezi.jpg",
      "description" : "",
      "available" : true,
      "tags" : [ ],
      "alt_text" : "Veg Jalfrezi",
      "category_id" : "main-course",
      "is_vegetarian" : true,
      "is_vegan" : false,
      "is_spicy" : false
    }, {
      "id" : "stuffed-tomato",
      "name" : "Stuffed Tomato",
      "price" : 269,
      "image" : "static/images/dishes/stuffed-tomato.jpg",
      "description" : "",
      "available" : true,
      "tags" : [ ],
      "alt_text" : "Stuffed Tomato",
      "category_id" : "main-course",
      "is_vegetarian" : true,
      "is_vegan" : false,
      "is_spicy" : false
    }, {
      "id" : "mushroom-mutter-masala",
      "name" : "Mushroom Mutter Masala",
      "price" : 269,
      "image" : "static/images/dishes/mushroom-mutter-masala.jpg",
      "description" : "",
      "available" : true,
      "tags" : [ ],
      "alt_text" : "Mushroom Mutter Masala",
      "category_id" : "main-course",
      "is_vegetarian" : true,
      "is_vegan" : false,
      "is_spicy" : false
    }, {
      "id" : "methi-malai-mutter-white-gravy",
      "name" : "Methi Malai Mutter (White Gravy)",
      "price" : 309,
      "image" : "static/images/dishes/methi-malai-mutter.jpg",
      "description" : "",
      "available" : true,
      "tags" : [ ],
      "alt_text" : "Methi Malai Mutter",
      "category_id" : "main-course",
      "is_vegetarian" : true,
      "is_vegan" : false,
      "is_spicy" : false
    }, {
      "id" : "kaju-curry-white-gravy",
      "name" : "Kaju Curry (White Gravy)",
      "price" : 329,
      "image" : "static/images/dishes/kaju-curry.jpg",
      "description" : "",
      "available" : true,
      "tags" : [ ],
      "alt_text" : "Kaju Curry",
      "category_id" : "main-course",
      "is_vegetarian" : true,
      "is_vegan" : false,
      "is_spicy" : false
    }, {
      "id" : "kaju-masala-red-gravy",
      "name" : "Kaju Masala (Red Gravy)",
      "price" : 309,
      "image" : "static/images/dishes/kaju-masala.jpg",
      "description" : "",
      "available" : true,
      "tags" : [ ],
      "alt_text" : "Kaju Masala",
      "category_id" : "main-course",
      "is_vegetarian" : true,
      "is_vegan" : false,
      "is_spicy" : false
    }, {
      "id" : "veg-kofta",
      "name" : "Veg Kofta",
      "price" : 209,
      "image" : "static/images/dishes/veg-kofta.jpg",
      "description" : "",
      "available" : true,
      "tags" : [ ],
      "alt_text" : "Veg Kofta",
      "category_id" : "main-course",
      "is_vegetarian" : true,
      "is_vegan" : false,
      "is_spicy" : false
    }, {
      "id" : "malai-kofta",
      "name" : "Malai Kofta",
      "price" : 269,
      "image" : "static/images/dishes/malai-kofta.jpg",
      "description" : "",
      "available" : true,
      "tags" : [ ],
      "alt_text" : "Malai Kofta",
      "category_id" : "main-course",
      "is_vegetarian" : true,
      "is_vegan" : false,
      "is_spicy" : false
    }, {
      "id" : "bhindi-kurkuri",
      "name" : "Bhindi Kurkuri",
      "price" : 209,
      "image" : "static/images/dishes/bhindi-kurkuri.jpg",
      "description" : "",
      "available" : true,
      "tags" : [ ],
      "alt_text" : "Bhindi Kurkuri",
      "category_id" : "main-course",
      "is_vegetarian" : true,
      "is_vegan" : false,
      "is_spicy" : false
    } ],
    "display_order" : 8
  }, {
    "id" : "paneer",
    "name" : "Apki Pasandida Paneer (Paneer Specialties)",
    "dishes" : [ {
      "id" : "palak-paneer",
      "name" : "Palak Paneer",
      "price" : 229,
      "image" : "static/images/dishes/palak-paneer.jpg",
      "description" : "",
      "available" : true,
      "tags" : [ ],
      "alt_text" : "Palak Paneer",
      "category_id" : "paneer",
      "is_vegetarian" : true,
      "is_vegan" : false,
      "is_spicy" : false
    }, {
      "id" : "mutter-paneer",
      "name" : "Mutter Paneer",
      "price" : 229,
      "image" : "static/images/dishes/mutter-paneer.jpg",
      "description" : "",
      "available" : true,
      "tags" : [ ],
      "alt_text" : "Mutter Paneer",
      "category_id" : "paneer",
      "is_vegetarian" : true,
      "is_vegan" : false,
      "is_spicy" : false
    }, {
      "id" : "chole-paneer",
      "name" : "Chole Paneer",
      "price" : 229,
      "image" : "static/images/dishes/chole-paneer.jpg",
      "description" : "",
      "available" : true,
      "tags" : [ ],
      "alt_text" : "Chole Paneer",
      "category_id" : "paneer",
      "is_vegetarian" : true,
      "is_vegan" : false,
      "is_spicy" : false
    }, {
      "id" : "kadai-paneer",
      "name" : "Kadai Paneer",
      "price" : 239,
      "image" : "static/images/dishes/kadai-paneer.jpg",
      "description" : "",
      "available" : true,
      "tags" : [ ],
      "alt_text" : "Kadai Paneer",
      "category_id" : "paneer",
      "is_vegetarian" : true,
      "is_vegan" : false,
      "is_spicy" : false
    }, {
      "id" : "paneer-butter-masala",
      "name" : "Paneer Butter Masala",
      "price" : 239,
      "image" : "static/images/dishes/paneer-butter-masala.jpg",
      "description" : "",
      "available" : true,
      "tags" : [ ],
      "alt_text" : "Paneer Butter Masala",
      "category_id" : "paneer",
      "is_vegetarian" : true,
      "is_vegan" : false,
      "is_spicy" : false
    }, {
      "id" : "tawa-paneer-masala",
      "name" : "Tawa Paneer Masala",
      "price" : 299,
      "image" : "static/images/dishes/tawa-paneer-masala.jpg",
      "description" : "",
      "available" : true,
      "tags" : [ ],
      "alt_text" : "Tawa Paneer Masala",
      "category_id" : "paneer",
      "is_vegetarian" : true,
      "is_vegan" : false,
      "is_spicy" : false
    }, {
      "id" : "paneer-handi",
      "name" : "Paneer Handi",
      "price" : 299,
      "image" : "static/images/dishes/paneer-handi.jpg",
      "description" : "",
      "available" : true,
      "tags" : [ ],
      "alt_text" : "Paneer Handi",
      "category_id" : "paneer",
      "is_vegetarian" : true,
      "is_vegan" : false,
      "is_spicy" : false
    }, {
      "id" : "shahi-paneer-white-gravy",
      "name" : "Shahi Paneer (White Gravy)",
      "price" : 299,
      "image" : "static/images/dishes/shahi-paneer.jpg",
      "description" : "",
      "available" : true,
      "tags" : [ ],
      "alt_text" : "Shahi Paneer",
      "category_id" : "paneer",
      "is_vegetarian" : true,
      "is_vegan" : false,
      "is_spicy" : false
    }, {
      "id" : "paneer-lababdar",
      "name" : "Paneer Lababdar",
      "price" : 299,
      "image" : "static/images/dishes/paneer-lababdar.jpg",
      "description" : "",
      "available" : true,
      "tags" : [ ],
      "alt_text" : "Paneer Lababdar",
      "category_id" : "paneer",
      "is_vegetarian" : true,
      "is_vegan" : false,
      "is_spicy" : false
    }, {
      "id" : "paneer-chatpata",
      "name" : "Paneer Chatpata",
      "price" : 299,
      "image" : "static/images/dishes/paneer-chatpata.jpg",
      "description" : "",
      "available" : true,
      "tags" : [ ],
      "alt_text" : "Paneer Chatpata",
      "category_id" : "paneer",
      "is_vegetarian" : true,
      "is_vegan" : false,
      "is_spicy" : false
    }, {
      "id" : "paneer-achari",
      "name" : "Paneer Achari",
      "price" : 299,
      "image" : "static/images/dishes/paneer-achari.jpg",
      "description" : "",
      "available" : true,
      "tags" : [ ],
      "alt_text" : "Paneer Achari",
      "category_id" : "paneer",
      "is_vegetarian" : true,
      "is_vegan" : false,
      "is_spicy" : false
    }, {
      "id" : "paneer-pasanda",
      "name" : "Paneer Pasanda",
      "price" : 309,
      "image" : "static/images/dishes/paneer-pasanda.jpg",
      "description" : "",
      "available" : true,
      "tags" : [ ],
      "alt_text" : "Paneer Pasanda",
      "category_id" : "paneer",
      "is_vegetarian" : true,
      "is_vegan" : false,
      "is_spicy" : false
    }, {
      "id" : "paneer-bhurji",
      "name" : "Paneer Bhurji",
      "price" : 309,
      "image" : "static/images/dishes/paneer-bhurji.jpg",
      "description" : "",
      "available" : true,
      "tags" : [ ],
      "alt_text" : "Paneer Bhurji",
      "category_id" : "paneer",
      "is_vegetarian" : true,
      "is_vegan" : false,
      "is_spicy" : false
    }, {
      "id" : "paneer-tikka-masala",
      "name" : "Paneer Tikka Masala",
      "price" : 369,
      "image" : "static/images/dishes/paneer-tikka-masala.jpg",
      "description" : "",
      "available" : true,
      "tags" : [ ],
      "alt_text" : "Paneer Tikka Masala",
      "category_id" : "paneer",
      "is_vegetarian" : true,
      "is_vegan" : false,
      "is_spicy" : false
    }, {
      "id" : "paneer-jalfrezi",
      "name" : "Paneer Jalfrezi",
      "price" : 309,
      "image" : "static/images/dishes/paneer-jalfrezi.jpg",
      "description" : "",
      "available" : true,
      "tags" : [ ],
      "alt_text" : "Paneer Jalfrezi",
      "category_id" : "paneer",
      "is_vegetarian" : true,
      "is_vegan" : false,
      "is_spicy" : false
    } ],
    "display_order" : 9
  }, {
    "id" : "rice",
    "name" : "Basmati Khazana (Rice Dishes)",
    "dishes" : [ {
      "id" : "plain-rice",
      "name" : "Plain Rice",
      "price" : 149,
      "image" : "static/images/dishes/plain-rice.jpg",
      "description" : "",
      "available" : true,
      "tags" : [ ],
      "alt_text" : "Plain Rice",
      "category_id" : "rice",
      "is_vegetarian" : true,
      "is_vegan" : false,
      "is_spicy" : false
    }, {
      "id" : "jeera-rice",
      "name" : "Jeera Rice",
      "price" : 169,
      "image" : "static/images/dishes/jeera-rice.jpg",
      "description" : "",
      "available" : true,
      "tags" : [ ],
      "alt_text" : "Jeera Rice",
      "category_id" : "rice",
      "is_vegetarian" : true,
      "is_vegan" : false,
      "is_spicy" : false
    }, {
      "id" : "dal-khichdi",
      "name" : "Dal Khichdi",
      "price" : 189,
      "image" : "static/images/dishes/dal-khichdi.jpg",
      "description" : "",
      "available" : true,
      "tags" : [ ],
      "alt_text" : "Dal Khichdi",
      "category_id" : "rice",
      "is_vegetarian" : true,
      "is_vegan" : false,
      "is_spicy" : false
    }, {
      "id" : "veg-pulao",
      "name" : "Veg Pulao",
      "price" : 209,
      "image" : "static/images/dishes/veg-pulao.jpg",
      "description" : "",
      "available" : true,
      "tags" : [ ],
      "alt_text" : "Veg Pulao",
      "category_id" : "rice",
      "is_vegetarian" : true,
      "is_vegan" : false,
      "is_spicy" : false
    }, {
      "id" : "veg-biryani-with-raita",
      "name" : "Veg Biryani with Raita",
      "price" : 259,
      "image" : "static/images/dishes/veg-biryani.jpg",
      "description" : "",
      "available" : true,
      "tags" : [ ],
      "alt_text" : "Veg Biryani",
      "category_id" : "rice",
      "is_vegetarian" : true,
      "is_vegan" : false,
      "is_spicy" : false
    }, {
      "id" : "veg-handi-biryani",
      "name" : "Veg Handi Biryani",
      "price" : 269,
      "image" : "static/images/dishes/veg-handi-biryani.jpg",
      "description" : "",
      "available" : true,
      "tags" : [ ],
      "alt_text" : "Veg Handi Biryani",
      "category_id" : "rice",
      "is_vegetarian" : true,
      "is_vegan" : false,
      "is_spicy" : false
    }, {
      "id" : "punjabi-khichdi",
      "name" : "Punjabi Khichdi",
      "price" : 189,
      "image" : "static/images/dishes/punjabi-khichdi.jpg",
      "description" : "",
      "available" : true,
      "tags" : [ ],
      "alt_text" : "Punjabi Khichdi",
      "category_id" : "rice",
      "is_vegetarian" : true,
      "is_vegan" : false,
      "is_spicy" : false
    } ],
    "display_order" : 10
  }, {
    "id" : "dal",
    "name" : "Dal Ki Kya Baat (Lentil Dishes)",
    "dishes" : [ {
      "id" : "dal-fry",
      "name" : "Dal Fry",
      "price" : 149,
      "image" : "static/images/dishes/dal-fry.jpg",
      "description" : "",
      "available" : true,
      "tags" : [ ],
      "alt_text" : "Dal Fry",
      "category_id" : "dal",
      "is_vegetarian" : true,
      "is_vegan" : false,
      "is_spicy" : false
    }, {
      "id" : "dal-handi",
      "name" : "Dal Handi",
      "price" : 189,
      "image" : "static/images/dishes/dal-handi.jpg",
      "description" : "",
      "available" : true,
      "tags" : [ ],
      "alt_text" : "Dal Handi",
      "category_id" : "dal",
      "is_vegetarian" : true,
      "is_vegan" : false,
      "is_spicy" : false
    }, {
      "id" : "dal-dhabe-wali",
      "name" : "Dal Dhabe Wali",
      "price" : 189,
      "image" : "static/images/dishes/dal-dhabe-wali.jpg",
      "description" : "",
      "available" : true,
      "tags" : [ ],
      "alt_text" : "Dal Dhabe Wali",
      "category_id" : "dal",
      "is_vegetarian" : true,
      "is_vegan" : false,
      "is_spicy" : false
    }, {
      "id" : "dal-makhani",
      "name" : "Dal Makhani",
      "price" : 189,
      "image" : "static/images/dishes/dal-makhani.jpg",
      "description" : "",
      "available" : true,
      "tags" : [ ],
      "alt_text" : "Dal Makhani",
      "category_id" : "dal",
      "is_vegetarian" : true,
      "is_vegan" : false,
      "is_spicy" : false
    } ],
    "display_order" : 11
  }, {
    "id" : "snacks",
    "name" : "Halka Phulka (Light Snacks)",
    "dishes" : [ {
      "id" : "pav-bhaji",
      "name" : "Pav Bhaji",
      "price" : 169,
      "image" : "static/images/dishes/pav-bhaji.jpg",
      "description" : "",
      "available" : true,
      "tags" : [ ],
      "alt_text" : "Pav Bhaji",
      "category_id" : "snacks",
      "is_vegetarian" : true,
      "is_vegan" : false,
      "is_spicy" : false
    }, {
      "id" : "chole-bhature",
      "name" : "Chole Bhature",
      "price" : 169,
      "image" : "static/images/dishes/chole-bhature.jpg",
      "description" : "",
      "available" : true,
      "tags" : [ ],
      "alt_text" : "Chole Bhature",
      "category_id" : "snacks",
      "is_vegetarian" : true,
      "is_vegan" : false,
      "is_spicy" : false
    } ],
    "display_order" : 12
  }, {
    "id" : "desserts",
    "name" : "Mithe Mey Kuch (Desserts)",
    "dishes" : [ {
      "id" : "gulab-jamun",
      "name" : "Gulab Jamun",
      "price" : 65,
      "image" : "static/images/dishes/gulab-jamun.jpg",
      "description" : "",
      "available" : true,
      "tags" : [ ],
      "alt_text" : "Gulab Jamun",
      "category_id" : "desserts",
      "is_vegetarian" : true,
      "is_vegan" : false,
      "is_spicy" : false
    }, {
      "id" : "rasgulla",
      "name" : "Rasgulla",
      "price" : 65,
      "image" : "static/images/dishes/rasgulla.jpg",
      "description" : "",
      "available" : true,
      "tags" : [ ],
      "alt_text" : "Rasgulla",
      "category_id" : "desserts",
      "is_vegetarian" : true,
      "is_vegan" : false,
      "is_spicy" : false
    }, {
      "id" : "rabdi",
      "name" : "Rabdi",
      "price" : 89,
      "image" : "static/images/dishes/rabdi.jpg",
      "description" : "",
      "available" : true,
      "tags" : [ ],
      "alt_text" : "Rabdi",
      "category_id" : "desserts",
      "is_vegetarian" : true,
      "is_vegan" : false,
      "is_spicy" : false
    } ],
    "display_order" : 13
  }, {
    "id" : "cold-beverages",
    "name" : "Thanda (Cold Beverages)",
    "dishes" : [ {
      "id" : "fresh-lime-soda",
      "name" : "Fresh Lime Soda",
      "price" : 52,
      "image" : "static/images/dishes/fresh-lime-soda.jpg",
      "description" : "",
      "available" : true,
      "tags" : [ ],
      "alt_text" : "Fresh Lime Soda",
      "category_id" : "cold-beverages",
      "is_vegetarian" : true,
      "is_vegan" : false,
      "is_spicy" : false
    }, {
      "id" : "fresh-lime-water",
      "name" : "Fresh Lime Water",
      "price" : 52,
      "image" : "static/images/dishes/fresh-lime-water.jpg",
      "description" : "",
      "available" : true,
      "tags" : [ ],
      "alt_text" : "Fresh Lime Water",
      "category_id" : "cold-beverages",
      "is_vegetarian" : true,
      "is_vegan" : false,
      "is_spicy" : false
    }, {
      "id" : "jaljeera",
      "name" : "Jaljeera",
      "price" : 59,
      "image" : "static/images/dishes/jaljeera.jpg",
      "description" : "",
      "available" : true,
      "tags" : [ ],
      "alt_text" : "Jaljeera",
      "category_id" : "cold-beverages",
      "is_vegetarian" : true,
      "is_vegan" : false,
      "is_spicy" : false
    }, {
      "id" : "masala-chaas",
      "name" : "Masala Chaas",
      "price" : 60,
      "image" : "static/images/dishes/masala-chaas.jpg",
      "description" : "",
      "available" : true,
      "tags" : [ ],
      "alt_text" : "Masala Chaas",
      "category_id" : "cold-beverages",
      "is_vegetarian" : true,
      "is_vegan" : false,
      "is_spicy" : false
    }, {
      "id" : "cold-coffee",
      "name" : "Cold Coffee",
      "price" : 85,
      "image" : "static/images/dishes/cold-coffee.jpg",
      "description" : "",
      "available" : true,
      "tags" : [ ],
      "alt_text" : "Cold Coffee",
      "category_id" : "cold-beverages",
      "is_vegetarian" : true,
      "is_vegan" : false,
      "is_spicy" : false
    }, {
      "id" : "cold-coffee-with-ice-cream",
      "name" : "Cold Coffee with Ice Cream",
      "price" : 149,
      "image" : "static/images/dishes/cold-coffee-ice-cream.jpg",
      "description" : "",
      "available" : true,
      "tags" : [ ],
      "alt_text" : "Cold Coffee with Ice Cream",
      "category_id" : "cold-beverages",
      "is_vegetarian" : true,
      "is_vegan" : false,
      "is_spicy" : false
    }, {
      "id" : "pineapple/mosambi/mix-juice",
      "name" : "Pineapple/Mosambi/Mix Juice",
      "price" : 119,
      "image" : "static/images/dishes/juice.jpg",
      "description" : "",
      "available" : true,
      "tags" : [ ],
      "alt_text" : "Juice",
      "category_id" : "cold-beverages",
      "is_vegetarian" : true,
      "is_vegan" : false,
      "is_spicy" : false
    }, {
      "id" : "vanilla-shake",
      "name" : "Vanilla Shake",
      "price" : 159,
      "image" : "static/images/dishes/vanilla-shake.jpg",
      "description" : "",
      "available" : true,
      "tags" : [ ],
      "alt_text" : "Vanilla Shake",
      "category_id" : "cold-beverages",
      "is_vegetarian" : true,
      "is_vegan" : false,
      "is_spicy" : false
    }, {
      "id" : "chocolate-shake",
      "name" : "Chocolate Shake",
      "price" : 150,
      "image" : "static/images/dishes/chocolate-shake.jpg",
      "description" : "",
      "available" : true,
      "tags" : [ ],
      "alt_text" : "Chocolate Shake",
      "category_id" : "cold-beverages",
      "is_vegetarian" : true,
      "is_vegan" : false,
      "is_spicy" : false
    }, {
      "id" : "kiwi-cooler",
      "name" : "Kiwi Cooler",
      "price" : 149,
      "image" : "static/images/dishes/kiwi-cooler.jpg",
      "description" : "",
      "available" : true,
      "tags" : [ ],
      "alt_text" : "Kiwi Cooler",
      "category_id" : "cold-beverages",
      "is_vegetarian" : true,
      "is_vegan" : false,
      "is_spicy" : false
    }, {
      "id" : "mint-mojito",
      "name" : "Mint Mojito",
      "price" : 149,
      "image" : "static/images/dishes/mint-mojito.jpg",
      "description" : "",
      "available" : true,
      "tags" : [ ],
      "alt_text" : "Mint Mojito",
      "category_id" : "cold-beverages",
      "is_vegetarian" : true,
      "is_vegan" : false,
      "is_spicy" : false
    } ],
    "display_order" : 14
  }, {
    "id" : "hot-beverages",
    "name" : "Garam (Hot Beverages)",
    "dishes" : [ {
      "id" : "tea",
      "name" : "Tea",
      "price" : 45,
      "image" : "static/images/dishes/tea.jpg",
      "description" : "",
      "available" : true,
      "tags" : [ ],
      "alt_text" : "Tea",
      "category_id" : "hot-beverages",
      "is_vegetarian" : true,
      "is_vegan" : false,
      "is_spicy" : false
    }, {
      "id" : "coffee",
      "name" : "Coffee",
      "price" : 60,
      "image" : "static/images/dishes/coffee.jpg",
      "description" : "",
      "available" : true,
      "tags" : [ ],
      "alt_text" : "Coffee",
      "category_id" : "hot-beverages",
      "is_vegetarian" : true,
      "is_vegan" : false,
      "is_spicy" : false
    }, {
      "id" : "tomato-soup",
      "name" : "Tomato Soup",
      "price" : 149,
      "image" : "static/images/dishes/tomato-soup.jpg",
      "description" : "",
      "available" : true,
      "tags" : [ ],
      "alt_text" : "Tomato Soup",
      "category_id" : "hot-beverages",
      "is_vegetarian" : true,
      "is_vegan" : false,
      "is_spicy" : false
    }, {
      "id" : "clear-soup",
      "name" : "Clear Soup",
      "price" : 149,
      "image" : "static/images/dishes/clear-soup.jpg",
      "description" : "",
      "available" : true,
      "tags" : [ ],
      "alt_text" : "Clear Soup",
      "category_id" : "hot-beverages",
      "is_vegetarian" : true,
      "is_vegan" : false,
      "is_spicy" : false
    }, {
      "id" : "veg-manchow-soup",
      "name" : "Veg Manchow Soup",
      "price" : 149,
      "image" : "static/images/dishes/veg-manchow-soup.jpg",
      "description" : "",
      "available" : true,
      "tags" : [ ],
      "alt_text" : "Veg Manchow Soup",
      "category_id" : "hot-beverages",
      "is_vegetarian" : true,
      "is_vegan" : false,
      "is_spicy" : false
    }, {
      "id" : "hot-n-sour-soup",
      "name" : "Hot N Sour Soup",
      "price" : 149,
      "image" : "static/images/dishes/hot-n-sour-soup.jpg",
      "description" : "",
      "available" : true,
      "tags" : [ ],
      "alt_text" : "Hot N Sour Soup",
      "category_id" : "hot-beverages",
      "is_vegetarian" : true,
      "is_vegan" : false,
      "is_spicy" : false
    }, {
      "id" : "sweet-corn-soup",
      "name" : "Sweet Corn Soup",
      "price" : 149,
      "image" : "static/images/dishes/sweet-corn-soup.jpg",
      "description" : "",
      "available" : true,
      "tags" : [ ],
      "alt_text" : "Sweet Corn Soup",
      "category_id" : "hot-beverages",
      "is_vegetarian" : true,
      "is_vegan" : false,
      "is_spicy" : false
    } ],
    "display_order" : 15
  }, {
    "id" : "chaat",
    "name" : "Chaat Chatori (Street Food)",
    "dishes" : [ {
      "id" : "pani-puri",
      "name" : "Pani Puri",
      "price" : 60,
      "image" : "static/images/dishes/pani-puri.jpg",
      "description" : "",
      "available" : true,
      "tags" : [ ],
      "alt_text" : "Pani Puri",
      "category_id" : "chaat",
      "is_vegetarian" : true,
      "is_vegan" : false,
      "is_spicy" : false
    }, {
      "id" : "dahi-puri",
      "name" : "Dahi Puri",
      "price" : 85,
      "image" : "static/images/dishes/dahi-puri.jpg",
      "description" : "",
      "available" : true,
      "tags" : [ ],
      "alt_text" : "Dahi Puri",
      "category_id" : "chaat",
      "is_vegetarian" : true,
      "is_vegan" : false,
      "is_spicy" : false
    }, {
      "id" : "bhelpuri",
      "name" : "Bhelpuri",
      "price" : 85,
      "image" : "static/images/dishes/bhelpuri.jpg",
      "description" : "",
      "available" : true,
      "tags" : [ ],
      "alt_text" : "Bhelpuri",
      "category_id" : "chaat",
      "is_vegetarian" : true,
      "is_vegan" : false,
      "is_spicy" : false
    }, {
      "id" : "papdi-chaat",
      "name" : "Papdi Chaat",
      "price" : 85,
      "image" : "static/images/dishes/papdi-chaat.jpg",
      "description" : "",
      "available" : true,
      "tags" : [ ],
      "alt_text" : "Papdi Chaat",
      "category_id" : "chaat",
      "is_vegetarian" : true,
      "is_vegan" : false,
      "is_spicy" : false
    }, {
      "id" : "chole-tikki",
      "name" : "Chole Tikki",
      "price" : 90,
      "image" : "static/images/dishes/chole-tikki.jpg",
      "description" : "",
      "available" : true,
      "tags" : [ ],
      "alt_text" : "Chole Tikki",
      "category_id" : "chaat",
      "is_vegetarian" : true,
      "is_vegan" : false,
      "is_spicy" : false
    } ],
    "display_order" : 16
  } ]
}